header2whatever/__init__.py
header2whatever/config.py
header2whatever/default_hooks.py
header2whatever/parse.py
header2whatever/preprocess.py
header2whatever/util.py
header2whatever/version.py
header2whatever/_pcpp/__init__.py
header2whatever/_pcpp/evaluator.py
header2whatever/_pcpp/preprocessor.py
header2whatever/_pcpp/ply/ply/__init__.py
header2whatever/_pcpp/ply/ply/cpp.py
header2whatever/_pcpp/ply/ply/ctokens.py
header2whatever/_pcpp/ply/ply/lex.py
header2whatever/_pcpp/ply/ply/yacc.py
header2whatever/_pcpp/ply/ply/ygen.py
header2whatever-0.4.8.dist-info/LICENSE
header2whatever-0.4.8.dist-info/METADATA
header2whatever-0.4.8.dist-info/WHEEL
header2whatever-0.4.8.dist-info/entry_points.txt
header2whatever-0.4.8.dist-info/top_level.txt
header2whatever-0.4.8.dist-info/RECORD
