Metadata-Version: 2.1
Name: header2whatever
Version: 0.4.8
Summary: Generate files from C/C++ headers using jinja2 templates
Home-page: https://github.com/virtualroadside/header2whatever
Author: Dustin Spicuzza
Author-email: dustin@virtualroadside.com
License: Apache 2.0
Keywords: c++ cpp codegen generator header jinja2 template
Platform: UNKNOWN
Classifier: Operating System :: OS Independent
Classifier: Environment :: Console
Classifier: Programming Language :: Python
Classifier: License :: OSI Approved :: Apache Software License
Requires-Dist: robotpy-cppheaderparser (>=5.1.0)
Requires-Dist: jinja2
Requires-Dist: pyyaml
Requires-Dist: schematics (>=2.1.1)
